mux.v
module mux(
    a,
    b,
    out,
    ctrl
);

    input [7:0] a,b;
    input ctrl;
    output reg[7:0] out;

    always @(*) begin
        case (ctrl)
            1'b0: out <= a;
            1'b1: out <= b; 
        endcase
    end
endmodule

mux31.v
module mux31(
    a,
    b,
    c,
    out,
    ctrl
);

    input [7:0] a,b,c;
    input [1:0] ctrl;
    output reg[7:0] out;

    always @(*) begin
        case (ctrl)
            2'b00: out <= a;
            2'b01: out <= b;
            2'b10: out <= c; 
        endcase
    end
endmodule

stack.v
module stack(
    data_i,
    opcode,
    clk,
    data_o
);
    input clk;
    input [7:0] data_i;
    input [3:0] opcode;
    output reg[7:0] data_o;

    reg [7:0] stp = 8'h00;
    reg [7:0] stack[0:255];

    always @(posedge clk) begin
        #3;
        //PUSH Reg
        if(opcode == 4'b1101) begin
            stack[stp] <= data_i;
            stp <= stp + 1;
        end else if(opcode == 4'b1110) begin
            stack[stp] <= data_i;
            stp <= stp + 1;
        end else if(opcode == 4'b1111) begin
            stp <= stp-1;
            //has to say stp-1
            data_o <= stack[stp-1];
        end
    end

endmodule

memory.v
module mem(
    clk,
    opcode,
    reg1,
    reg2,
    reg3,
    sreg1
);

    input clk;
    input [7:0] sreg1;
    output reg[3:0] opcode,reg1,reg2,reg3;
    reg [15:0] memory[0:255];
    reg[7:0] counter = 8'h00;
    
    initial begin
        $readmemh("program.mem", memory);    
    end
    
    always @(posedge clk) begin
        opcode <= memory[counter][15:12];
        reg1 <= memory[counter][11:8];
        reg2 <= memory[counter][7:4];
        reg3 <= memory[counter][3:0];
        //Next command controlled by jmp command
        //Unconditional jump
        if(memory[counter][15:12] == 4'b1000) begin
            counter <= counter + {memory[counter][11],memory[counter][11],memory[counter][11],memory[counter][11],memory[counter][11:8]};
        end 
        //Conditional jump BZ
        else if(memory[counter][15:12] == 4'b1001 && sreg1[5] == 1) begin
            counter <= counter + {memory[counter][11],memory[counter][11],memory[counter][11],memory[counter][11],memory[counter][11:8]};
        end 
        //Conditional jump BN
        else if(memory[counter][15:12] == 4'b1010 && sreg1[7] == 1) begin
            counter <= counter + {memory[counter][11],memory[counter][11],memory[counter][11],memory[counter][11],memory[counter][11:8]};
        end else if(memory[counter][15:12] == 4'b1100) begin
            counter <= counter;
        end else begin
            counter <= counter+1;
        end
    end

endmodule

register.v
module register_bank(
    clk,
    data_i,
    reg1,
    reg2,
    reg3,
    reg1_o,
    reg2_o,
    reg3_o,
    sreg1_i,
    sreg1_o,
    write_enable
);
    input clk;
    input write_enable;
    input[7:0] data_i, sreg1_i;
    input[3:0] reg1,reg2,reg3;

    output reg[7:0] reg1_o, reg2_o, reg3_o, sreg1_o;
    reg [7:0] reg_bank [0:15]; 
    reg [7:0] SREG1 = 8'b00000000;

    always @(posedge clk) begin
        #4;
        if(write_enable)
            reg_bank[reg1] <= data_i;
            SREG1 <= sreg1_i;
            sreg1_o <= sreg1_i; 
    end

    always @(posedge clk) begin
        #2;
        reg1_o <= reg_bank[reg1];
        reg2_o <= reg_bank[reg2];
        reg3_o <= reg_bank[reg3];
        sreg1_o <= SREG1;
    end

endmodule

alu.v
module alu(
    clk,
    a,
    b,
    sreg1_i,
    out,
    sreg1_o,
    opcode
);


    input clk;
    input[7:0] a,b, sreg1_i;
    input[3:0] opcode;
    output reg[7:0] out, sreg1_o;

    always @(posedge clk) begin
        #3;
        //Pass through SREG if nothing happens
        sreg1_o <= sreg1_i;
        case(opcode)
            4'b0000:out <= a&b;
            4'b0001:out <= a|b;
            4'b0010: begin
                out <= a+b;
                //Handle zero flag
                if(a+b == 8'h00) begin
                    sreg1_o[5] <= 1;
                end else
                    sreg1_o[5] <= 0;
                //Handle overflow flag
                if(a+b < a || a+b < b) begin
                    sreg1_o[6] <= 1;
                end else
                    sreg1_o[6] <= 0;
            end
            4'b0011: begin
                out <= a-b;
                //Handle zero flag
                if(a == b) begin
                    sreg1_o[5] <= 1;
                end else
                    sreg1_o[5] <= 0;
                //Handle negative flag
                if(b > a) begin
                    sreg1_o[7] <= 1;
                end else
                    sreg1_o[7] <= 0;
            end
            //Same code for immediate commands
            4'b0100:out <= a&b;
            4'b0101:out <= a|b;
            4'b0110: begin
                out <= a+b;
                //Handle zero flag
                if(a+b == 8'h00) begin
                    sreg1_o[5] <= 1;
                end else
                    sreg1_o[5] <= 0;
                //Handle overflow flag
                if(a+b > 8'hff) begin
                    sreg1_o[6] <= 1;
                end else
                    sreg1_o[6] <= 0;
            end
            4'b0111: begin
                out <= a-b;
                //Handle zero flag
                if(a == b) begin
                    sreg1_o[5] <= 1;
                end else
                    sreg1_o[5] <= 0;
                //Handle negative flag
                if(b > a) begin
                    sreg1_o[7] <= 1;
                end else
                    sreg1_o[7] <= 0;
            end
        endcase
    end  

endmodule

ctrl_unit.v
`include "alu.v"
`include "memory.v"
`include "register.v"
`include "mux.v"
`include "stack.v"
`include "mux31.v"


module ctrl_unit(
    clk
);

    input clk;
    wire [7:0] alu_in1, alu_in2;
    wire [7:0] alu_out;
    wire [3:0] opcode, reg1, reg2, reg3;
    wire [7:0] reg1_out, reg2_out, reg3_out, sreg1_o, sreg1_i;
    wire [7:0] data_in;
    wire [7:0] stack_in, stack_out;
    //0 for register, 1 for immediat.e
    reg mux_ctrl;
    reg write_enable;
    //Controls data in of reg_bank
    //Decides between ALU Output(00), SET command(01), STACK Output(10)
    reg [1:0] ctrl_data_in;
    //Immediate if 1, reg if 0
    reg stack_in_ctrl;

    alu alu1(
        .clk(clk),
        .a(alu_in1),
        .b(alu_in2),
        .sreg1_i(sreg1_o),
        .out(alu_out),
        .sreg1_o(sreg1_i),
        .opcode(opcode)
    );

    register_bank bank1(
        .clk(clk),
        .data_i(data_in),
        .reg1(reg1),
        .reg2(reg2),
        .reg3(reg3),
        .reg1_o(reg1_out),
        .reg2_o(reg2_out),
        .reg3_o(reg3_out),
        .sreg1_o(sreg1_o),
        .sreg1_i(sreg1_i),
        .write_enable(write_enable)
    );

    mem mem1(
        .clk(clk),
        .opcode(opcode),
        .reg1(reg1),
        .reg2(reg2),
        .reg3(reg3),
        .sreg1(sreg1_o)
    );

    stack stack1(
        .clk(clk),
        .data_i(stack_in),
        .opcode(opcode),
        .data_o(stack_out)
    );

    mux mux1(
        //Only reg3 arg is immediate
        //To change set b to {4'b0000, reg2}
        .a(reg2_out),
        .b(reg2_out),
        .out(alu_in1),
        .ctrl(mux_ctrl)
    );

    mux mux2(
        .a(reg3_out),
        .b({4'b0000,reg3}),
        .out(alu_in2),
        .ctrl(mux_ctrl)
    );

    mux31 mux3(
        .a(alu_out),
        .b({reg2, reg3}),
        .c(stack_out),
        .out(data_in),
        .ctrl(ctrl_data_in)
    );

    mux mux4(
        .a(reg1_out),
        .b({reg2, reg3}),
        .out(stack_in),
        .ctrl(stack_in_ctrl)
    );

    always @(posedge clk) begin
        #1; //Delay to wait for new opcode
        //Standard on, off for jmp command
        write_enable <= 1;
        //Disable writing if jmp instruction or HLT command or push stack command
        if(opcode == 4'b1000 || opcode == 4'b1001 || opcode == 4'b1010 || opcode == 4'b1100 || opcode == 4'b1101 || opcode == 4'b1110) begin
            write_enable <= 0;
        end
        //Decides between immediate and register source for alu commands
        //Determined by bit 2 of the opcode_
        mux_ctrl <= opcode[2];

        //Standard selection is ALU out
        ctrl_data_in <= 2'b00;
        //Uses reg2 and reg3 if SET command
        if(opcode == 4'b1011) begin
            ctrl_data_in <= 2'b01;
        end
        //Use STACK Out if POP command
        else if(opcode == 4'b1111) begin
            ctrl_data_in <= 2'b10;
        end

        //Control stack in
        //Standard is register as input
        stack_in_ctrl <= 0;
        //If immediate command, use immediate instead
        if(opcode == 4'b1110) begin
            stack_in_ctrl <= 1;
        end

    end


endmodule

ctrl_tb.v
`include "ctrl_unit.v"

module testbench;

    reg clk;

    ctrl_unit uut(.clk(clk));

    initial begin
        $dumpfile("wave.vcd");
        $dumpvars(3);
    end

    initial begin
        clk = 0;
        forever begin
            #10;
            clk <= ~clk;
        end
    end

    initial begin
        #1000;
        $finish;
    end
endmodule

wave.vcd
$date
	Sun Mar 09 13:36:53 2025
$end
$version
	Icarus Verilog
$end
$timescale
	1s
$end
$scope module testbench $end
$var reg 1 ! clk $end
$scope module uut $end
$var wire 1 ! clk $end
$var wire 8 " stack_out [7:0] $end
$var wire 8 # stack_in [7:0] $end
$var wire 8 $ sreg1_o [7:0] $end
$var wire 8 % sreg1_i [7:0] $end
$var wire 8 & reg3_out [7:0] $end
$var wire 4 ' reg3 [3:0] $end
$var wire 8 ( reg2_out [7:0] $end
$var wire 4 ) reg2 [3:0] $end
$var wire 8 * reg1_out [7:0] $end
$var wire 4 + reg1 [3:0] $end
$var wire 4 , opcode [3:0] $end
$var wire 8 - data_in [7:0] $end
$var wire 8 . alu_out [7:0] $end
$var wire 8 / alu_in2 [7:0] $end
$var wire 8 0 alu_in1 [7:0] $end
$var reg 2 1 ctrl_data_in [1:0] $end
$var reg 1 2 mux_ctrl $end
$var reg 1 3 stack_in_ctrl $end
$var reg 1 4 write_enable $end
$scope module alu1 $end
$var wire 1 ! clk $end
$var wire 8 5 sreg1_i [7:0] $end
$var wire 4 6 opcode [3:0] $end
$var wire 8 7 b [7:0] $end
$var wire 8 8 a [7:0] $end
$var reg 8 9 out [7:0] $end
$var reg 8 : sreg1_o [7:0] $end
$upscope $end
$scope module bank1 $end
$var wire 1 ! clk $end
$var wire 8 ; sreg1_i [7:0] $end
$var wire 1 4 write_enable $end
$var wire 4 < reg3 [3:0] $end
$var wire 4 = reg2 [3:0] $end
$var wire 4 > reg1 [3:0] $end
$var wire 8 ? data_i [7:0] $end
$var reg 8 @ SREG1 [7:0] $end
$var reg 8 A reg1_o [7:0] $end
$var reg 8 B reg2_o [7:0] $end
$var reg 8 C reg3_o [7:0] $end
$var reg 8 D sreg1_o [7:0] $end
$upscope $end
$scope module mem1 $end
$var wire 1 ! clk $end
$var wire 8 E sreg1 [7:0] $end
$var reg 8 F counter [7:0] $end
$var reg 4 G opcode [3:0] $end
$var reg 4 H reg1 [3:0] $end
$var reg 4 I reg2 [3:0] $end
$var reg 4 J reg3 [3:0] $end
$upscope $end
$scope module mux1 $end
$var wire 8 K a [7:0] $end
$var wire 8 L b [7:0] $end
$var wire 1 2 ctrl $end
$var reg 8 M out [7:0] $end
$upscope $end
$scope module mux2 $end
$var wire 8 N a [7:0] $end
$var wire 8 O b [7:0] $end
$var wire 1 2 ctrl $end
$var reg 8 P out [7:0] $end
$upscope $end
$scope module mux3 $end
$var wire 8 Q a [7:0] $end
$var wire 8 R b [7:0] $end
$var wire 2 S ctrl [1:0] $end
$var wire 8 T c [7:0] $end
$var reg 8 U out [7:0] $end
$upscope $end
$scope module mux4 $end
$var wire 8 V a [7:0] $end
$var wire 8 W b [7:0] $end
$var wire 1 3 ctrl $end
$var reg 8 X out [7:0] $end
$upscope $end
$scope module stack1 $end
$var wire 1 ! clk $end
$var wire 8 Y data_i [7:0] $end
$var wire 4 Z opcode [3:0] $end
$var reg 8 [ data_o [7:0] $end
$var reg 8 \ stp [7:0] $end
$upscope $end
$upscope $end
$upscope $end
$enddefinitions $end
#0
$dumpvars
b0 \
bx [
bx Z
bx Y
bx X
bx W
bx V
bx U
bx T
bx S
bx R
bx Q
bx P
b0xxxx O
bx N
bx M
bx L
bx K
bx J
bx I
bx H
bx G
b0 F
bx E
bx D
bx C
bx B
bx A
b0 @
bx ?
bx >
bx =
bx <
bx ;
bx :
bx 9
bx 8
bx 7
bx 6
bx 5
x4
x3
x2
bx 1
bx 0
bx /
bx .
bx -
bx ,
bx +
bx *
bx )
bx (
bx '
bx &
bx %
bx $
bx #
bx "
0!
$end
#10
b1 F
b1010 O
b1010 '
b1010 <
b1010 J
b11010 W
b11010 R
b1 )
b1 =
b1 I
b1 +
b1 >
b1 H
b1011 ,
b1011 6
b1011 G
b1011 Z
1!
#11
b11010 -
b11010 ?
b11010 U
03
b1 1
b1 S
02
14
#12
b0 $
b0 5
b0 D
b0 E
#13
b0 %
b0 :
b0 ;
#20
0!
#30
b11001 -
b11001 ?
b11001 U
b10 F
b11001 W
b11001 R
b1001 O
b1001 '
b1001 <
b1001 J
b10 +
b10 >
b10 H
1!
#31
b1 1
b1 S
#32
b11010 0
b11010 8
b11010 M
b11010 (
b11010 B
b11010 K
b11010 L
#40
0!
#50
b0 -
b0 ?
b0 U
b11 F
b0 O
b0 '
b0 <
b0 J
b0 W
b0 R
b0 )
b0 =
b0 I
b1 +
b1 >
b1 H
b1101 ,
b1101 6
b1101 G
b1101 Z
1!
#51
bx -
bx ?
bx U
b0 /
b0 7
b0 P
b0 1
b0 S
12
04
#52
bx 0
bx 8
bx M
b11010 #
b11010 X
b11010 Y
bx (
bx B
bx K
bx L
b11010 *
b11010 A
b11010 V
#53
b1 \
#60
0!
#70
b100 F
b10 +
b10 >
b10 H
1!
#71
04
#72
b11001 #
b11001 X
b11001 Y
b11001 *
b11001 A
b11001 V
#73
b10 \
#80
0!
#90
b101 F
b1 +
b1 >
b1 H
b1111 ,
b1111 6
b1111 G
b1111 Z
1!
#91
b10 1
b10 S
14
#92
b11010 #
b11010 X
b11010 Y
b11010 *
b11010 A
b11010 V
#93
b11001 -
b11001 ?
b11001 U
b11001 "
b11001 T
b11001 [
b1 \
#100
0!
#110
b0 +
b0 >
b0 H
b1100 ,
b1100 6
b1100 G
b1100 Z
1!
#111
bx -
bx ?
bx U
b0 1
b0 S
04
#112
bx #
bx X
bx Y
bx *
bx A
bx V
#120
0!
#130
1!
#131
04
#140
0!
#150
1!
#151
04
#160
0!
#170
1!
#171
04
#180
0!
#190
1!
#191
04
#200
0!
#210
1!
#211
04
#220
0!
#230
1!
#231
04
#240
0!
#250
1!
#251
04
#260
0!
#270
1!
#271
04
#280
0!
#290
1!
#291
04
#300
0!
#310
1!
#311
04
#320
0!
#330
1!
#331
04
#340
0!
#350
1!
#351
04
#360
0!
#370
1!
#371
04
#380
0!
#390
1!
#391
04
#400
0!
#410
1!
#411
04
#420
0!
#430
1!
#431
04
#440
0!
#450
1!
#451
04
#460
0!
#470
1!
#471
04
#480
0!
#490
1!
#491
04
#500
0!
#510
1!
#511
04
#520
0!
#530
1!
#531
04
#540
0!
#550
1!
#551
04
#560
0!
#570
1!
#571
04
#580
0!
#590
1!
#591
04
#600
0!
#610
1!
#611
04
#620
0!
#630
1!
#631
04
#640
0!
#650
1!
#651
04
#660
0!
#670
1!
#671
04
#680
0!
#690
1!
#691
04
#700
0!
#710
1!
#711
04
#720
0!
#730
1!
#731
04
#740
0!
#750
1!
#751
04
#760
0!
#770
1!
#771
04
#780
0!
#790
1!
#791
04
#800
0!
#810
1!
#811
04
#820
0!
#830
1!
#831
04
#840
0!
#850
1!
#851
04
#860
0!
#870
1!
#871
04
#880
0!
#890
1!
#891
04
#900
0!
#910
1!
#911
04
#920
0!
#930
1!
#931
04
#940
0!
#950
1!
#951
04
#960
0!
#970
1!
#971
04
#980
0!
#990
1!
#991
04
